genus/__init__.py
genus-0.0.1.dist-info/METADATA
genus-0.0.1.dist-info/WHEEL
genus-0.0.1.dist-info/entry_points.txt
genus-0.0.1.dist-info/top_level.txt
genus-0.0.1.dist-info/RECORD
