Metadata-Version: 2.1
Name: genus
Version: 0.0.1
Summary: ai in development
Home-page: https://github.com/genus/genus
Author: genus
Author-email: genus.ai@gmail.com
License: MIT
Classifier: License :: OSI Approved :: MIT License
Classifier: Programming Language :: Python :: 3
Classifier: Programming Language :: Python :: 3.7
